{
  "rep_name": "Landon Vaughan",
  "rep_id": "4826542193295360",
  "rep_title": "Manager",
  "call_id": "4936920882552832",
  "branch": "Dallas Einstein Moving Company",
  "duration_min": 6.4,
  "datetime_ct": "2026-06-21 15:53 CT",
  "speakers": [
    "Landon Vaughan",
    "Vincent Ndar"
  ],
  "transcript": "Landon Vaughan: Hey, this is Landon with Einstein moving. I was calling for vent.\nVincent Ndar: Yes.\nLandon Vaughan: Hey! Yeah, so, and trying to get that looks like on the 7th of July I was just seeing if the about it.\nVincent Ndar: Yes.\nLandon Vaughan: Okay. And then your email just to confirm I have OD as in dog, H-I. And then Vince @yahoo.com.\nVincent Ndar: That's correct.\nLandon Vaughan: And then just to confirm as well. We're starting at 2455 Jefferson court and that's in Arlington and then we're going to be driving all the way out to 1864 men. Drive in Hazlett looks like about a forty minute drive there.\nVincent Ndar: Yes.\nLandon Vaughan: You're in a two bedroom apartment on the first floor currently. Do you know the square footage of your current apartment by any chance?\nVincent Ndar: Again.\nLandon Vaughan: Do you know the square footage of the apartment you're in currently by any chance?\nVincent Ndar: Oh, I'm not sure about it. Alright, I think it should be on 7700 and something.\nLandon Vaughan: Okay, is it a one or two bed?\nVincent Ndar: I'm not wrong. It's a two bedroom.\nLandon Vaughan: Okay, gotcha, and we're on the first floor. Gotcha. Do you want to walk me through just like a quick inventory of like, the furniture items we need to move that'll kind of help me out as far as like time?\nVincent Ndar: Yes.\nVincent Ndar: Yes, so.\nVincent Ndar: I'll have like a one table have a bed of 14 the bunches and one king with the mattress.\nVincent Ndar: Then I have a seven seater couch.\nVincent Ndar: A small dining table with chairs.\nLandon Vaughan: Okay.\nVincent Ndar: And then I have a I have a drawer, 1111 drawer and 222 side lamps.\nVincent Ndar: I have a small Chester just a fridge.\nLandon Vaughan: Okay.\nVincent Ndar: There. Okay, yeah, then I have a coffee table.\nVincent Ndar: Tank and I have a great.\nLandon Vaughan: A grill. Okay, is that on the patio?\nVincent Ndar: Yes.\nVincent Ndar: Yes, and then go ahead.\nLandon Vaughan: Gotcha, then do you?\nLandon Vaughan: No, I was just gonna add something else we can go ahead first.\nVincent Ndar: And then I have a, I might have maybe.\nVincent Ndar: I think maybe ten boxes.\nLandon Vaughan: Okay.\nLandon Vaughan: Cool. And then as far as, do you have like a no garage or like any storage or anything like that on site? You won't need us to make like a stop at the storage unit or anything.\nVincent Ndar: Where are like for apartment?\nLandon Vaughan: Yeah, just any like, do, you don't need us to stop anywhere else or do you don't have like a storage unit at your apartment, nothing like that.\nVincent Ndar: No, no, no, no, no, no, yeah, it just from one apartment to the house.\nLandon Vaughan: Okay, gotcha, awesome.\nLandon Vaughan: And then.\nLandon Vaughan: Alright. And then the house it's 1800 square foot one story home. How many bedrooms do you guys have the new? How many bedrooms do you have at the new spot?\nVincent Ndar: So the bedrooms are four bedrooms.\nLandon Vaughan: Four bedroom, awesome! And then, parking gonna be pretty simple at both locations. We're not going to have to worry about any like any, any, just difficult parking or difficult access.\nVincent Ndar: No, no, there's no dis parking.\nLandon Vaughan: Okay, gotcha.\nLandon Vaughan: Alright, man. Then that sounds good. I'll just kind of get into our pricing and everything. It's super simple. So we're just time based, the only time we ever have any additional fees is when we have to go like out of town or anything like that. So to get our truck back from, there's $115 trip fee. But other than that everything is just included in an hourly rate. So it's $200 and two hour $202 an hour for two. Move our team everything's included. So, we'll pad and wrap disassemble reassemble like the full nine as far as all that goes and you're not paying any like additional costs for any of that stuff. We don't have any like credit card fees or there's nothing like that. Added, no taxes. I estimated our typical range for a two bedroom apartment it's anywhere from four to six hours. I kind of have it right in the middle, for four and a half to five hours, if it took them four and a half hours that will come out out to $1,024 to get the full thing up and then just to give you a number on five hours, if it's a five hours that'd be $1,125 just to kind of give you two numbers to have.\nVincent Ndar: So you said that's include the, that's the assembling and reassembling.\nLandon Vaughan: Yes, sir. Yeah, that has the full that, that's everything included. The movers. They've got like tool bags with them and everything like that. There's no, you don't pay any extra costs for them like taking your bed a part and reassembling it or anything like that.\nVincent Ndar: Okay. Can you, can you send me that quote through my email then I just look at it.\nLandon Vaughan: Yeah, yeah, of course. I'll send it all over to you. Yeah, of course. And then just to kind of couple of just a few other things we don't require any deposits and then we don't have any cancellation fees. The only, like, the only fluctuation with price is they would be so Tuesday through Thursday, those are our best value prices. So I have you set for Tuesday and how that's what the 7th of July if you, if you needed to like reschedule to like a Friday or a Saturday. The hour the rate goes up a little bit and then on Monday, on Sunday and Monday as well it's just not as high as Friday and Saturday, so, so I would just like to, to go at that point as well.\nVincent Ndar: Sunday is high or Sundays low.\nLandon Vaughan: Sunday is lower than Friday and Saturday but it is higher than Tuesday through Thursday. So the hourly rate for Sunday. Just give me one second I can.\nVincent Ndar: So did you put it on Tuesday?\nLandon Vaughan: Yeah, yeah, I have it set for Tuesday now. So you got the Tuesday pricing for now. Yes, sir.\nVincent Ndar: Okay, alright. Just send, send it to me I'll look at it.\nLandon Vaughan: Yes sir.\nLandon Vaughan: Yeah, I'll send it over to you and I'll send you the quote for five hours just the highest end of the range and then you don't pay for any time that's not spent. So if they only take four hours or whatever it is, you guys only pay for that time.\nVincent Ndar: Okay. Alright.\nLandon Vaughan: Alright. Alright Vincent, well I appreciate you man. Thanks for taking my call. You have a good rest of your weekend.\nVincent Ndar: Oh, alright, thanks.\nLandon Vaughan: Alrighty, bye.",
  "line_count": 61
}